dpi_textract/__init__.py
dpi_textract-0.0.2.dist-info/METADATA
dpi_textract-0.0.2.dist-info/WHEEL
dpi_textract-0.0.2.dist-info/RECORD
