Metadata-Version: 2.1
Name: dpi-textract
Version: 0.0.2
Summary: Library for Extracting Data from Guatemalan ID Cards (DPI) in Images Using Textract
Project-URL: Homepage, https://github.com/LuisMa9L/dpi_textract_
Project-URL: Bug Tracker, https://github.com/LuisMa9L/dpi_textract_/issues
Author-email: Luis Manuel Morales <soy.lmml@gmail.com>
Classifier: License :: OSI Approved :: MIT License
Classifier: Operating System :: OS Independent
Classifier: Programming Language :: Python :: 3
Classifier: Topic :: Software Development :: Libraries :: Python Modules
Requires-Python: >=3.7
Requires-Dist: boto3>=1.28.0
